{
  "items": [
    {
      "title": "BUMPER Retail Expansion 2025.(DEMO)",
      "src": "media/BUMPER Retail_Expansion_2025.(DEMO).mp4",
      "type": "video",
      "filterType": "Video"
    },
    {
      "title": "IKEA International School Of Helsingborg",
      "src": "media/IKEA___International_School_of_Helsingborg.mp4",
      "type": "video",
      "filterType": "Video"
    },
    {
      "title": "Moonwalkers",
      "src": "media/Moonwalkers.jpg",
      "type": "image",
      "filterType": "Image"
    },
    {
      "title": "Moonwalkers1",
      "src": "media/Moonwalkers1.jpg",
      "type": "image",
      "filterType": "Image"
    },
    {
      "title": "NetZero Bumper",
      "src": "media/NetZero_Bumper.mov",
      "type": "video",
      "filterType": "Video"
    }
  ]
}
